emailpy/__init__.py
emailpy/__main__.py
emailpy/gethostport.py
emailpy/parse.py
emailpy/read.py
emailpy/send.py
emailpy/servers.py
emailpy/sort.py
emailpy/util.py
emailpy-0.3.0.data/scripts/emailpy
emailpy-0.3.0.dist-info/METADATA
emailpy-0.3.0.dist-info/WHEEL
emailpy-0.3.0.dist-info/top_level.txt
emailpy-0.3.0.dist-info/RECORD
