Metadata-Version: 2.1
Name: emailpy
Version: 0.3.0
Summary: A Python interface to interact with emails. 
Home-page: https://pypi.org/project/emailpy
Author: Sandra Mattar
Author-email: sandrawmattar1@gmail.com
License: UNKNOWN
Platform: UNKNOWN
Classifier: Programming Language :: Python :: 3
Classifier: Topic :: Communications :: Email
Requires-Dist: ospy
